populate_data_deterministic/__init__.py
populate_data_deterministic/populate_data_deterministic.py
populate_data_deterministic/providers.py
populate_data_deterministic-0.2.5.dist-info/AUTHORS.rst
populate_data_deterministic-0.2.5.dist-info/LICENSE
populate_data_deterministic-0.2.5.dist-info/METADATA
populate_data_deterministic-0.2.5.dist-info/WHEEL
populate_data_deterministic-0.2.5.dist-info/top_level.txt
populate_data_deterministic-0.2.5.dist-info/RECORD
