Metadata-Version: 2.1
Name: populate-data-deterministic
Version: 0.2.5
Summary: Populate initial data for development purposes & testing easily.
Home-page: https://github.com/tigeraniya/populate_data_deterministic
Author: Arun Tigeraniya
Author-email: tigeraniya@gmail.com
License: MIT license
Keywords: populate_data_deterministic
Platform: UNKNOWN
Classifier: Development Status :: 2 - Pre-Alpha
Classifier: Intended Audience :: Developers
Classifier: License :: OSI Approved :: MIT License
Classifier: Natural Language :: English
Classifier: Programming Language :: Python :: 3
Classifier: Programming Language :: Python :: 3.6
Classifier: Programming Language :: Python :: 3.7
Classifier: Programming Language :: Python :: 3.8
Requires-Python: >=3.6
License-File: LICENSE
License-File: AUTHORS.rst
Requires-Dist: django (>3)
